Metadata-Version: 2.1
Name: franciszek-slomka-school
Version: 1.0.0
Summary: School abstraction library
Home-page: UNKNOWN
License: UNKNOWN
Platform: UNKNOWN
